__init__.py
namespace.py
resource.py
types.py
utils.py
fastapi_namespace/__init__.py
fastapi_namespace/namespace.py
fastapi_namespace/resource.py
fastapi_namespace/types.py
fastapi_namespace/utils.py
fastapi_namespace/tests/__init__.py
fastapi_namespace/tests/test.py
fastapi_namespace/tests/test2.py
tests/__init__.py
tests/test.py
fastapi_namespace-0.1.4.dist-info/LICENSE
fastapi_namespace-0.1.4.dist-info/METADATA
fastapi_namespace-0.1.4.dist-info/WHEEL
fastapi_namespace-0.1.4.dist-info/top_level.txt
fastapi_namespace-0.1.4.dist-info/RECORD
